chi_index/__init__.py
chi_index/metrics.py
chi_index/model.py
chi_index/utils/__init__.py
chi_index/utils/plot_utils.py
chi_index/utils/tools.py
chi_index-2.1.dist-info/LICENSE.txt
chi_index-2.1.dist-info/METADATA
chi_index-2.1.dist-info/WHEEL
chi_index-2.1.dist-info/top_level.txt
chi_index-2.1.dist-info/RECORD
