Metadata-Version: 2.1
Name: chi-index
Version: 2.1
Summary: External Clustering Validation Chi index
Home-page: https://github.com/josemarialuna/ChiIndex
Author: José María Luna-Romera
Author-email: josemarialunaromera@gmail.com
License: MIT
Download-URL: https://github.com/josemarialuna/ChiIndex/tarball/0.1
Keywords: chi index,cvi,clustering,machine learning
Platform: UNKNOWN
Classifier: Development Status :: 3 - Alpha
Classifier: Intended Audience :: Science/Research
Classifier: Topic :: Software Development :: Build Tools
Classifier: License :: OSI Approved :: MIT License
Classifier: Programming Language :: Python :: 3
Classifier: Programming Language :: Python :: 3.7
Classifier: Programming Language :: Python :: 3.8
Classifier: Programming Language :: Python :: 3.9
Classifier: Programming Language :: Python :: 3.10
License-File: LICENSE.txt
Requires-Dist: sklearn
Requires-Dist: scipy
Requires-Dist: numpy
Requires-Dist: pandas
